pyDHC/__init__.py
pyDHC-1.3.3.dist-info/LICENSE
pyDHC-1.3.3.dist-info/METADATA
pyDHC-1.3.3.dist-info/WHEEL
pyDHC-1.3.3.dist-info/top_level.txt
pyDHC-1.3.3.dist-info/RECORD
