Metadata-Version: 2.1
Name: pyDHC
Version: 1.3.3
Summary: Communication to Devolo Home Control hub
Home-page: https://github.com/autinerd/python-devoloDHC
Author: Sidney Kuyateh
Author-email: sidneyjohn23@icloud.com
License: UNKNOWN
Platform: UNKNOWN
Classifier: Programming Language :: Python :: 3
Classifier: License :: OSI Approved :: MIT License
Classifier: Operating System :: OS Independent
Classifier: Development Status :: 4 - Beta
Classifier: Intended Audience :: Developers
Requires-Dist: certifi
